bioml_tasks/__about__.py
bioml_tasks/__init__.py
bioml_tasks/client.py
bioml_tasks/exceptions.py
bioml_tasks-0.2.0.dist-info/LICENSE
bioml_tasks-0.2.0.dist-info/METADATA
bioml_tasks-0.2.0.dist-info/WHEEL
bioml_tasks-0.2.0.dist-info/top_level.txt
bioml_tasks-0.2.0.dist-info/RECORD
