Metadata-Version: 2.1
Name: bioml-tasks
Version: 0.2.0
Summary: Python client for BioML Tasks
Author: BioML Tasks, Inc.
License: 
Project-URL: homepage, https://biomltasks.com
Project-URL: repository, https://github.com/bioml-tasks/bioml-tasks-python
Requires-Python: >=3.8
License-File: LICENSE
Requires-Dist: packaging
Requires-Dist: pydantic >1
Requires-Dist: requests >2
Provides-Extra: dev
Requires-Dist: black ; extra == 'dev'
Requires-Dist: mypy ; extra == 'dev'
Requires-Dist: pytest ; extra == 'dev'
Requires-Dist: responses ; extra == 'dev'
Requires-Dist: ruff ; extra == 'dev'
